listmonk_mcp/__init__.py
listmonk_mcp/client.py
listmonk_mcp/config.py
listmonk_mcp/exceptions.py
listmonk_mcp/models.py
listmonk_mcp/server.py
listmonk_mcp-0.1.0.dist-info/METADATA
listmonk_mcp-0.1.0.dist-info/WHEEL
listmonk_mcp-0.1.0.dist-info/entry_points.txt
listmonk_mcp-0.1.0.dist-info/licenses/LICENSE
listmonk_mcp-0.1.0.dist-info/RECORD
