Metadata-Version: 2.4
Name: listmonk-mcp
Version: 0.1.0
Summary: MCP server for Listmonk newsletter management
Author-email: Rohan Verma <hello@rohanverma.net>
License-Expression: MIT
License-File: LICENSE
Requires-Python: >=3.11
Requires-Dist: httpx>=0.24.0
Requires-Dist: mcp>=1.2.0
Requires-Dist: pydantic-settings>=2.0.0
Requires-Dist: pydantic[email]>=2.0.0
Requires-Dist: typer>=0.9.0
Provides-Extra: dev
Requires-Dist: black>=23.0.0; extra == 'dev'
Requires-Dist: mypy>=1.5.0; extra == 'dev'
Requires-Dist: pytest-asyncio>=0.21.0; extra == 'dev'
Requires-Dist: pytest-httpx>=0.21.0; extra == 'dev'
Requires-Dist: pytest-mock>=3.10.0; extra == 'dev'
Requires-Dist: pytest>=7.0.0; extra == 'dev'
Requires-Dist: ruff>=0.1.0; extra == 'dev'
Provides-Extra: docs
Requires-Dist: mkdocs-git-revision-date-localized-plugin>=1.2.0; extra == 'docs'
Requires-Dist: mkdocs-material>=9.5.0; extra == 'docs'
